{"nodes": [{"id": "I go to school with my dad"}, {"id": "I go to school on foot"}, {"id": "I go to school by bus"}, {"id": "pancakes"}, {"id": "strawberries"}], "links": [{"source": "I go to school with my dad", "target": "I go to school on foot", "value": 0.5284438133239746}, {"source": "I go to school with my dad", "target": "I go to school by bus", "value": 0.4857020974159241}, {"source": "I go to school with my dad", "target": "pancakes", "value": 0.06965211033821106}, {"source": "I go to school with my dad", "target": "strawberries", "value": -0.07676278054714203}, {"source": "I go to school on foot", "target": "I go to school by bus", "value": 0.5938054919242859}, {"source": "I go to school on foot", "target": "pancakes", "value": 0.1260325014591217}, {"source": "I go to school on foot", "target": "strawberries", "value": -0.015600240789353848}, {"source": "I go to school by bus", "target": "pancakes", "value": 0.09605010598897934}, {"source": "I go to school by bus", "target": "strawberries", "value": -0.026953117921948433}, {"source": "pancakes", "target": "strawberries", "value": 0.18747657537460327}]}